{
    "67255": {
        "name": "Inter Volet avec dérogation",
		"configuration": {
                            "version": "1.3",
							"update": "Ajout du statut numérique",
							"nbunit": "2",
							"672551": {
								"ref_legrand": "67255",
								"family": "SHUTTER",
								"nom_interne": "Monte/Descente/Stop",
								"btn": "Monte/Descente/Stop",
								"unit": "1",
								"unit_status": "2",
								"possibility": "COMMAND",
								"function_code": "50",
								"unit_code": "4",
								"server_opt": "NULL",
								"commentaire": "COMMAND=Mouvement volet"
								},
							"672552": {
								"ref_legrand": "67255",
								"family": "SHUTTER",
								"nom_interne": "STATUS",
								"btn": "Memoire Monte/Descente/Stop",
								"unit": "2",
								"unit_status": "2",
								"possibility": "ACTION,STATUS,MEMORY",
								"function_code": "50",
								"unit_code": "139",
								"server_opt": "NULL",
								"commentaire": "NULL"
								}
                        },				
        "subtype": {
            "00": {
                "name": "Defaut",
                "commands": [
                    {
                        "name": "Status",
                        "type": "info",
						"subtype": "string",
                        "isVisible": 1,
						"isHistorized": 0,
                        "unite": "",
						"eventOnly": 1,
						"logicalId": "status2",	
						"configuration": {
                            "returnStateValue": "",
                            "returnStateTime": "",
							"unit": "2"
                        }				
					},
					{
                        "name": "Status Numerique",
                        "type": "info",
						"subtype": "numeric",
                        "isVisible": 0,
						"isHistorized": 0,
                        "unite": "",
						"logicalId": "statusnum2",	
						"configuration": {
                            "returnStateValue": "",
                            "returnStateTime": "",
							"unit": "2"
                        },
						"display": {
							"generic_type": "FLAP_STATE"
						}					
					},
					{
                        "name": "Ouvrir",
                        "type": "action",
						"subtype": "other",
                        "isVisible": 1,
						"logicalId": "*#WHO#*1*#WHERE##IDUNIT##MEDIA###",
						"configuration": {
							"whatdim": {
								"what": "2",
								"dim": "NULL",
								"nom": "Move_Up"
							},	
							"unit": "2",
							"where": "Unicast"
                        },
						"display": {
							"generic_type": "FLAP_UP"
						}
                    },
                    {
                        "name": "Fermer",
                        "type": "action",
						"subtype": "other",
                        "isVisible": 1,
						"logicalId": "*#WHO#*2*#WHERE##IDUNIT##MEDIA###",
						"configuration": {
							"whatdim": {
								"what": "1",
								"dim": "NULL",
								"nom": "Move_Down"
							},
							"unit": "2",
							"where": "Unicast"
						},
						"display": {
							"generic_type": "FLAP_DOWN"
						}
					},
                    {
                        "name": "Stop",
                        "type": "action",
						"subtype": "other",
                        "isVisible": 1,
						"logicalId": "*#WHO#*0*#WHERE##IDUNIT##MEDIA###",
						"configuration": {
							"whatdim": {
								"what": "0",
								"dim": "NULL",
								"nom": "Move_Stop"
							},
							"unit": "2",
							"where": "Unicast"
						},
						"display": {
							"generic_type": "FLAP_STOP"
						}
                    },
					{
                        "name": "Ouvrir Scenario",
                        "type": "action",
						"subtype": "other",
                        "isVisible": 1,
						"logicalId": "*#WHO#*1*#WHERE##IDUNIT##MEDIA###",
						"configuration": {
							"whatdim": {
								"what": "2",
								"dim": "NULL",
								"nom": "Move_Up"
							},	
							"unit": "1",
							"where": "Multicast"
                        }
                    },
                    {
                        "name": "Fermer Scenario",
                        "type": "action",
						"subtype": "other",
                        "isVisible": 1,
						"logicalId": "*#WHO#*2*#WHERE##IDUNIT##MEDIA###",
						"configuration": {
							"whatdim": {
								"what": "1",
								"dim": "NULL",
								"nom": "Move_Down"
							},
							"unit": "1",
							"where": "Multicast"
						}
					},
                    {
                        "name": "Stop Scenario",
                        "type": "action",
						"subtype": "other",
                        "isVisible": 1,
						"logicalId": "*#WHO#*0*#WHERE##IDUNIT##MEDIA###",
						"configuration": {
							"whatdim": {
								"what": "0",
								"dim": "NULL",
								"nom": "Move_Stop"
							},
							"unit": "1",
							"where": "Multicast"
						}
                    }
                ]
            },
			"01": {
                "name": "Inversé",
                "commands": [
                    {
                        "name": "Status",
                        "type": "info",
						"subtype": "string",
                        "isVisible": 1,
						"isHistorized": 0,
                        "unite": "",
						"eventOnly": 1,
						"logicalId": "status2",	
						"configuration": {
                            "returnStateValue": "",
                            "returnStateTime": "",
							"unit": "2"
                        }				
					},
					{
                        "name": "Status Numerique",
                        "type": "info",
						"subtype": "numeric",
                        "isVisible": 0,
						"isHistorized": 0,
                        "unite": "",
						"logicalId": "statusnum2",	
						"configuration": {
                            "returnStateValue": "",
                            "returnStateTime": "",
							"unit": "2"
                        },
						"display": {
							"generic_type": "FLAP_STATE"
						}					
					},					
					{
                        "name": "Ouvrir",
                        "type": "action",
						"subtype": "other",
                        "isVisible": 1,
						"logicalId": "*#WHO#*2*#WHERE##IDUNIT##MEDIA###",
						"configuration": {
							"whatdim": {
								"what": "2",
								"dim": "NULL",
								"nom": "Move_Down"
							},
							"unit": "2",
							"where": "Unicast"
                        },
						"display": {
							"generic_type": "FLAP_UP"
						}
                    },
                    {
                        "name": "Fermer",
                        "type": "action",
						"subtype": "other",
                        "isVisible": 1,
						"logicalId": "*#WHO#*1*#WHERE##IDUNIT##MEDIA###",
						"configuration": {
							"whatdim": {
								"what": "1",
								"dim": "NULL",
								"nom": "Move_Up"
							},
							"unit": "2",
							"where": "Unicast"
						},
						"display": {
							"generic_type": "FLAP_DOWN"
						}
					},	
                    {
                        "name": "Stop",
                        "type": "action",
						"subtype": "other",
                        "isVisible": 1,
						"logicalId": "*#WHO#*0*#WHERE##IDUNIT##MEDIA###",
						"configuration": {
							"whatdim": {
								"what": "0",
								"dim": "NULL",
								"nom": "Move_Stop"
							},
							"unit": "2",
							"where": "Unicast"
						},
						"display": {
							"generic_type": "FLAP_STOP"
						}
                    },
					{
                        "name": "Ouvrir Scenario",
                        "type": "action",
						"subtype": "other",
                        "isVisible": 1,
						"logicalId": "*#WHO#*2*#WHERE##IDUNIT##MEDIA###",
						"configuration": {
							"whatdim": {
								"what": "2",
								"dim": "NULL",
								"nom": "Move_Down"
							},
							"unit": "1",
							"where": "Multicast"
                        }
                    },
                    {
                        "name": "Fermer Scenario",
                        "type": "action",
						"subtype": "other",
                        "isVisible": 1,
						"logicalId": "*#WHO#*1*#WHERE##IDUNIT##MEDIA###",
						"configuration": {
							"whatdim": {
								"what": "1",
								"dim": "NULL",
								"nom": "Move_Up"
							},
							"unit": "1",
							"where": "Multicast"
						}
					},
                    {
                        "name": "Stop Scenario",
                        "type": "action",
						"subtype": "other",
                        "isVisible": 1,
						"logicalId": "*#WHO#*0*#WHERE##IDUNIT##MEDIA###",
						"configuration": {
							"whatdim": {
								"what": "0",
								"dim": "NULL",
								"nom": "Move_Stop"
							},
							"unit": "1",
							"where": "Multicast"
						}
                    }
                ]
            }
        }
    }
}